pyhaab/__init__.py
pyhaab/__main__.py
pyhaab-4.0.0.dist-info/licenses/LICENSE.txt
pyhaab-4.0.0.dist-info/METADATA
pyhaab-4.0.0.dist-info/WHEEL
pyhaab-4.0.0.dist-info/top_level.txt
pyhaab-4.0.0.dist-info/RECORD
