Metadata-Version: 2.4
Name: pyhaab
Version: 4.0.0
Summary: Cisco switch inventory collector – update in place
Author-email: Ihaab Saeed <ihaabsaeed@gmail.com>
License: MIT
Project-URL: Homepage, https://github.com/ihaabsaeed2/pyhaab
Classifier: Programming Language :: Python :: 3
Classifier: License :: OSI Approved :: MIT License
Classifier: Intended Audience :: System Administrators
Requires-Python: >=3.9
License-File: LICENSE.txt
Requires-Dist: netmiko>=4.0.0
Requires-Dist: openpyxl>=3.1.2
Dynamic: license-file
